[
  {
    "make": "Toyota",
    "model": "Corolla",
    "year": "2018",
    "image": "https://e1.pxfuel.com/desktop-wallpaper/455/200/desktop-wallpaper-toyota-corolla-altis-white-2018-in-toyota-corolla-toyota-altis.jpg",
    "price": "30"
  },
  {
    "make": "Honda",
    "model": "Civic",
    "year": "2020",
    "image": "https://via.placeholder.com/200x150",
    "price": "35"
  },
  {
    "make": "Ford",
    "model": "Focus",
    "year": "2019",
    "image": "https://via.placeholder.com/200x150",
    "price": "32"
  }
]
